lcheapo/Peterson_noise_model.py
lcheapo/__init__.py
lcheapo/instrument_metadata.py
lcheapo/lc2SDS.py
lcheapo/lc2ms.py
lcheapo/lccut.py
lcheapo/lcdump.py
lcheapo/lcfix.py
lcheapo/lcheader.py
lcheapo/lcheapo_utils.py
lcheapo/lcinfo.py
lcheapo/lcplot.py
lcheapo/lcputexamples.py
lcheapo/lcread.py
lcheapo/spectral.py
lcheapo/version.py
lcheapo/yaml_json.py
lcheapo/_examples/20191107T14_SPOBS09_F02.raw.lch
lcheapo/_examples/BBOBS.lctest.yaml
lcheapo/_examples/calc_spectral.py
lcheapo/_examples/lc_print_bad_times.py
lcheapo/_examples/stations.lctest.yaml
lcheapo/_examples/tests.lctest.yaml
lcheapo/data/BBOBS1.INSU-IPGP.station.xml
lcheapo/data/HYDROCT1.INSU-IPGP.station.xml
lcheapo/data/SPOBS1.INSU-IPGP.station.xml
lcheapo/data/SPOBS2.INSU-IPGP.station.xml
lcheapo/data/SPOBS2.station.xml
lcheapo/data/lctest.schema.json
lcheapo/data/_old/.DS_Store
lcheapo/data/_old/BBOBS1.station.xml
lcheapo/data/subnetworks/HYDROCT1.INSU-IPGP.station.xml
lcheapo/data/subnetworks/HYDROCT1.INSU-IPGP.subnetwork.yaml
lcheapo/sds_tools/__init__.py
lcheapo/sds_tools/noise_models.py
lcheapo/sds_tools/sds_ppsds.py
lcheapo-2.1.dist-info/LICENSE.txt
lcheapo-2.1.dist-info/METADATA
lcheapo-2.1.dist-info/WHEEL
lcheapo-2.1.dist-info/entry_points.txt
lcheapo-2.1.dist-info/top_level.txt
lcheapo-2.1.dist-info/RECORD
