Metadata-Version: 2.1
Name: lcheapo
Version: 2.1
Summary: LCHEAPO data routines
Home-page: https://github.com/WayneCrawford/lcheapo
Author: Wayne Crawford
Author-email: crawford@ipgp.fr
Keywords: oceanography,marine,OBS
Classifier: Development Status :: 4 - Beta
Classifier: Environment :: Console
Classifier: Intended Audience :: Science/Research
Classifier: Intended Audience :: Developers
Classifier: License :: OSI Approved :: GNU General Public License v3 (GPLv3)
Classifier: Natural Language :: English
Classifier: Operating System :: OS Independent
Classifier: Programming Language :: Python :: 3.6
Classifier: Topic :: Scientific/Engineering
Classifier: Topic :: Scientific/Engineering :: Physics
Requires-Python: >=3.8
License-File: LICENSE.txt
Requires-Dist: obspy (>=1.1)
Requires-Dist: pyyaml (>5.0)
Requires-Dist: jsonschema (>=2.6)
Requires-Dist: jsonref (>=0.2)
Requires-Dist: progress (>=1.5)
Requires-Dist: numpy (<2.0)
Requires-Dist: sdpchainpy (>=1.0b2)
Requires-Dist: tiskitpy (>=0.4)
